{
  "date": "2026-02-09",
  "prices": {
    "USDTRY": "43.7800",
    "ALTIN": "7400.880",
    "USDPURE": "169060.0000",
    "EURTRY": "51.6590",
    "ONS": "4966.30",
    "EURUSD": 1.18,
    "USDKG": "168210.0",
    "EURKG": 142870,
    "GBPTRY": 59.444,
    "AYAR22": "7010.840",
    "CHFTRY": 56.476,
    "AUDTRY": 30.646,
    "KULCEALTIN": 7437.88,
    "CADTRY": 32.226,
    "XAUXAG": 63.94,
    "CEYREK_YENI": 12128,
    "SARTRY": 11.881,
    "CEYREK_ESKI": 12068,
    "USDCHF": "0.7850",
    "YARIM_YENI": 24248,
    "JPYTRY": 0.2779,
    "YARIM_ESKI": 24211,
    "AUDUSD": "0.7000",
    "TEK_YENI": 48274,
    "SEKTRY": 4.604,
    "TEK_ESKI": 48052,
    "DKKTRY": 6.766,
    "USDCAD": "1.3850",
    "ATA_YENI": 49680,
    "NOKTRY": 3.856,
    "ATA_ESKI": 49606,
    "USDSAR": "3.8050",
    "ATA5_YENI": 246869,
    "USDJPY": "159.46700",
    "ATA5_ESKI": 246499,
    "GBPUSD": "1.3580",
    "GREMESE_YENI": 120684,
    "GREMESE_ESKI": 119944,
    "AYAR14": "5310.570",
    "GUMUSTRY": 136.418,
    "XAGUSD": 77.92,
    "GUMUSUSD": 3116,
    "XPTUSD": 2111,
    "XPDUSD": 1711,
    "PLATIN": 67880,
    "PALADYUM": 55000
  }
}